CONTRIBUTING.md
LICENSE
MANIFEST.in
README.md
WORKSPACE
requirements.txt
setup.py
jaxline/__init__.py
jaxline/base_config.py
jaxline/conftest.py
jaxline/experiment.py
jaxline/platform.py
jaxline/train.py
jaxline/train_test.py
jaxline/utils.py
jaxline/utils_test.py
jaxline.egg-info/PKG-INFO
jaxline.egg-info/SOURCES.txt
jaxline.egg-info/dependency_links.txt
jaxline.egg-info/not-zip-safe
jaxline.egg-info/requires.txt
jaxline.egg-info/top_level.txt