Metadata-Version: 2.1
Name: jaxline
Version: 0.0.7
Summary: JAXline is a distributed JAX training framework.
Home-page: https://github.com/deepmind/jaxline
Author: DeepMind
Author-email: jaxline-copybara@google.com
License: Apache 2.0
Classifier: Development Status :: 4 - Beta
Classifier: Intended Audience :: Developers
Classifier: Intended Audience :: Education
Classifier: Intended Audience :: Science/Research
Classifier: License :: OSI Approved :: Apache Software License
Classifier: Programming Language :: Python :: 3
Classifier: Programming Language :: Python :: 3.6
Classifier: Programming Language :: Python :: 3.7
Classifier: Programming Language :: Python :: 3.8
Classifier: Topic :: Scientific/Engineering :: Mathematics
Classifier: Topic :: Software Development :: Libraries :: Python Modules
Classifier: Topic :: Software Development :: Libraries
Provides-Extra: jax
Provides-Extra: jaxlib
Provides-Extra: tensorflow
Provides-Extra: tensorflow with gpu
License-File: LICENSE
